{
  "sections": {
    "slideshow_f3JmXG": {
      "type": "slideshow",
      "blocks": {
        "slide_cDRiBK": {
          "type": "slide",
          "settings": {
            "image": "shopify:\/\/shop_images\/Screenshot_2024-05-01_at_11.35.58.png",
            "heading": "Welcome to Mantra Living",
            "heading_size": "h2",
            "subheading": "",
            "button_label": "SHOP EVERDAY LIVING",
            "link": "shopify:\/\/collections\/everyday-living-1",
            "button_style_secondary": false,
            "box_align": "middle-center",
            "show_text_box": false,
            "text_alignment": "center",
            "image_overlay_opacity": 0,
            "color_scheme": "accent-1",
            "text_alignment_mobile": "center"
          }
        },
        "slide_4BpqFB": {
          "type": "slide",
          "settings": {
            "image": "shopify:\/\/shop_images\/Screenshot_2024-05-13_at_11.03.12.png",
            "heading": "Welcome to Mantra Living",
            "heading_size": "h2",
            "subheading": "",
            "button_label": "SHOP TOWELS",
            "link": "shopify:\/\/collections\/towels-1",
            "button_style_secondary": false,
            "box_align": "middle-center",
            "show_text_box": false,
            "text_alignment": "center",
            "image_overlay_opacity": 0,
            "color_scheme": "accent-1",
            "text_alignment_mobile": "center"
          }
        },
        "slide_QVCke6": {
          "type": "slide",
          "settings": {
            "image": "shopify:\/\/shop_images\/Screenshot_2024-05-13_at_11.03.43.png",
            "heading": "Welcome to Mantra Living",
            "heading_size": "h2",
            "subheading": "",
            "button_label": "Shop Mugs & Jugs",
            "link": "shopify:\/\/collections\/mugs-1",
            "button_style_secondary": false,
            "box_align": "middle-center",
            "show_text_box": false,
            "text_alignment": "center",
            "image_overlay_opacity": 0,
            "color_scheme": "inverse",
            "text_alignment_mobile": "center"
          }
        }
      },
      "block_order": [
        "slide_cDRiBK",
        "slide_4BpqFB",
        "slide_QVCke6"
      ],
      "settings": {
        "layout": "full_bleed",
        "slide_height": "medium",
        "slider_visual": "dots",
        "auto_rotate": true,
        "change_slides_speed": 5,
        "image_behavior": "ambient",
        "show_text_below": true,
        "accessibility_info": "Slideshow about our brand"
      }
    },
    "multirow_3JtBwj": {
      "type": "multirow",
      "blocks": {
        "row_tp3TRk": {
          "type": "row",
          "settings": {
            "image": "shopify:\/\/shop_images\/IMG_0369.jpg",
            "caption": "",
            "heading": "Home. Lifestyle. Food. Garden.",
            "text": "<p>Mantra Living is a curation of the things that we love & are passionate about in all aspects of life. It is a celebration of the things that we believe add magic to one’s life: food, home, garden, lifestyle. <\/p><p> Mantra Living is inspired by the beauty of life itself and aims to inspire a beautiful way of living.<br\/><\/p>",
            "button_label": "",
            "button_link": ""
          }
        },
        "row_4HX4dN": {
          "type": "row",
          "settings": {
            "image": "shopify:\/\/shop_images\/DSCF2420_3.jpg",
            "caption": "",
            "heading": "Creation of Beautiful Spaces",
            "text": "<p>We want to inspire people to understand what makes a space feel more comfortable& homely with the aim to make people feel good about themselves in their spaces through the creation of a beautiful environment by which they surround themselves and which makes them feel happy. <\/p><p>Mantra Living explores what makes a meal with friends wonderful, a space inviting & homely, gardens thrive, and simply what makes life even more wonderful. <\/p>",
            "button_label": "Shop Everyday Living",
            "button_link": "shopify:\/\/collections\/everyday-living-1"
          }
        },
        "row_WgGCbp": {
          "type": "row",
          "settings": {
            "image": "shopify:\/\/shop_images\/DSCF0899.jpg",
            "caption": "",
            "heading": "Slow & Soulful",
            "text": "<p>Our philosophy is simple: less is more and the beauty of life lies in simplicity. We believe in the slow and soulful, in feeding the spirit with meaningful moments. <\/p><p>Join us on this journey of embracing the beauty and happiness in every aspect of life.<\/p>",
            "button_label": "Shop Lifestyle",
            "button_link": "shopify:\/\/collections\/lifestyle-1"
          }
        }
      },
      "block_order": [
        "row_tp3TRk",
        "row_4HX4dN",
        "row_WgGCbp"
      ],
      "settings": {
        "image_height": "adapt",
        "desktop_image_width": "medium",
        "heading_size": "h2",
        "text_style": "subtitle",
        "button_style": "primary",
        "desktop_content_position": "middle",
        "desktop_content_alignment": "left",
        "image_layout": "alternate-left",
        "section_color_scheme": "background-2",
        "row_color_scheme": "accent-2",
        "mobile_content_alignment": "left",
        "padding_top": 36,
        "padding_bottom": 36
      }
    },
    "collage_9QwDaH": {
      "type": "collage",
      "blocks": {
        "image_awKFbG": {
          "type": "image",
          "settings": {
            "image": "shopify:\/\/shop_images\/Screenshot_2024-05-01_at_11.48.30_12e65fad-6822-42b9-8586-812a98fc3613.png"
          }
        },
        "product_gGMpbz": {
          "type": "product",
          "settings": {
            "product": "green-tea-jug",
            "second_image": false
          }
        },
        "collection_zKfY77": {
          "type": "collection",
          "settings": {
            "collection": "jugs"
          }
        }
      },
      "block_order": [
        "image_awKFbG",
        "product_gGMpbz",
        "collection_zKfY77"
      ],
      "settings": {
        "heading": "Multimedia collage",
        "heading_size": "h1",
        "desktop_layout": "left",
        "mobile_layout": "collage",
        "card_styles": "product-card-wrapper",
        "color_scheme": "",
        "padding_top": 36,
        "padding_bottom": 36
      }
    },
    "custom_banner_Vh6Npc": {
      "type": "custom-banner",
      "settings": {
        "image": "shopify:\/\/shop_images\/Screenshot_2024-05-01_at_11.35.58.png",
        "image_2": "shopify:\/\/shop_images\/DSCF2904.jpg",
        "image_overlay_opacity": 0,
        "image_height": "medium",
        "desktop_content_position": "middle-center",
        "show_text_box": true,
        "desktop_content_alignment": "center",
        "color_scheme": "",
        "image_behavior": "none",
        "mobile_content_alignment": "center",
        "stack_images_on_mobile": true,
        "show_text_below": true
      }
    }
  },
  "order": [
    "slideshow_f3JmXG",
    "multirow_3JtBwj",
    "collage_9QwDaH",
    "custom_banner_Vh6Npc"
  ]
}
